.coveragerc
.editorconfig
.pre-commit-config.yaml
.readthedocs.yml
CONTRIBUTING.md
LICENSE
MANIFEST.in
README.md
README.pypi.md
pyproject.toml
pytest.ini
requirements.txt
setup.cfg
setup.py
docs/conf.py
docs/index.rst
docs/installation.rst
docs/readme.rst
docs/requirements.txt
docs/spelling_wordlist.txt
docs/usage.rst
docs/reference/financetda.rst
docs/reference/index.rst
src/.info/AUTHORS.md
src/.info/CHANGELOG.md
src/fintda/__init__.py
src/fintda/auxiliary.py
src/fintda/ftda.py
src/fintda.egg-info/PKG-INFO
src/fintda.egg-info/SOURCES.txt
src/fintda.egg-info/dependency_links.txt
src/fintda.egg-info/entry_points.txt
src/fintda.egg-info/not-zip-safe
src/fintda.egg-info/top_level.txt
src/fintda/data/data.csv
tests/auxiliary_test.py
tests/ftda_test.py